regex_generate_py-2023.3.7.dist-info/METADATA
regex_generate_py-2023.3.7.dist-info/WHEEL
regex_generate_py/__init__.py
regex_generate_py/regex_generate_py.cpython-311-darwin.so
regex_generate_py-2023.3.7.dist-info/RECORD
