Metadata-Version: 2.3
Name: regex_generate_py
Version: 2023.3.7
Classifier: Programming Language :: Rust
Classifier: Programming Language :: Python :: Implementation :: CPython
Classifier: Programming Language :: Python :: Implementation :: PyPy
Classifier: Topic :: Utilities
Classifier: Topic :: Text Processing :: General
Classifier: Topic :: Text Processing
Classifier: Topic :: Software Development :: Testing
Summary: Use regular expressions to generate text. This is the PyO3 Python binding of the Rust crate 'regex_generate'.
Requires-Python: >=3.8
